{
    "FLL-PVG": {
        "price": null,
        "route_info": null,
        "airline": null,
        "outbound_date": "2025-11-21",
        "return_date": "2025-11-30",
        "last_updated": "2026-04-08T03:51:40.877021",
        "status": "api_error: `outbound_date` cannot be in the past."
    },
    "MIA-PVG": {
        "price": null,
        "route_info": null,
        "airline": null,
        "outbound_date": "2025-11-21",
        "return_date": "2025-11-30",
        "last_updated": "2026-04-08T03:51:41.000631",
        "status": "api_error: `outbound_date` cannot be in the past."
    }
}